ci_environment/CiEnvironments.json
ci_environment/__init__.py
ci_environment/ci_environment.py
ci_environment/variable_expression.py
ci_environment-13.0.0.dist-info/licenses/LICENSE
ci_environment-13.0.0.dist-info/WHEEL
ci_environment-13.0.0.dist-info/METADATA
ci_environment-13.0.0.dist-info/RECORD
