Metadata-Version: 2.4
Name: ci-environment
Version: 13.0.0
Summary: This library detects the CI environment based on environment variables defined by CI servers.
Keywords: cucumber,ci
Author: Cucumber Limited
Author-email: Cucumber Limited <cukes@googlegroups.com>
License-Expression: MIT
License-File: LICENSE
Classifier: Development Status :: 4 - Beta
Classifier: Intended Audience :: Developers
Classifier: License :: OSI Approved :: MIT License
Classifier: Operating System :: POSIX
Classifier: Operating System :: Microsoft :: Windows
Classifier: Operating System :: MacOS :: MacOS X
Classifier: Topic :: Utilities
Classifier: Programming Language :: Python :: 3
Classifier: Programming Language :: Python :: 3.10
Classifier: Programming Language :: Python :: 3.11
Classifier: Programming Language :: Python :: 3.12
Classifier: Programming Language :: Python :: 3.13
Classifier: Programming Language :: Python :: 3.14
Maintainer: Konstantin Goloveshko
Maintainer-email: Konstantin Goloveshko <kostya.goloveshko@gmail.com>
Requires-Python: >=3.10
Project-URL: Changelog, https://github.com/cucumber/ci-environment/releases
Project-URL: Download, https://pypi.org/project/ci-environment/
Project-URL: Homepage, https://github.com/cucumber/ci-environment
Project-URL: Issues, https://github.com/cucumber/ci-environment/issues
Project-URL: Repository, https://github.com/cucumber/ci-environment
